guillotina_s3storage/__init__.py
guillotina_s3storage/interfaces.py
guillotina_s3storage/py.typed
guillotina_s3storage/storage.py
guillotina_s3storage/tests/__init__.py
guillotina_s3storage/tests/conftest.py
guillotina_s3storage/tests/fixtures.py
guillotina_s3storage/tests/mocks.py
guillotina_s3storage/tests/test_storage.py
guillotina_s3storage-5.0.10.dist-info/LICENSE
guillotina_s3storage-5.0.10.dist-info/METADATA
guillotina_s3storage-5.0.10.dist-info/WHEEL
guillotina_s3storage-5.0.10.dist-info/top_level.txt
guillotina_s3storage-5.0.10.dist-info/zip-safe
guillotina_s3storage-5.0.10.dist-info/RECORD
