Metadata-Version: 2.1
Name: guillotina-s3storage
Version: 5.0.10
Summary: s3 guillotina storage support
Home-page: https://pypi.python.org/pypi/guillotina_s3storage
Author: Ramon Navarro Bosch
Author-email: ramon@plone.org
License: GPL version 3
Keywords: async aiohttp guillotina s3
Platform: UNKNOWN
Classifier: Programming Language :: Python :: 3.6
Classifier: Topic :: Software Development :: Libraries :: Python Modules
Requires-Dist: setuptools
Requires-Dist: guillotina (<7,>=5.0.0)
Requires-Dist: aiohttp (<4.0.0,>3.0.0)
Requires-Dist: ujson
Requires-Dist: aiobotocore (==0.9.4)
Requires-Dist: botocore (==1.10.58)
Requires-Dist: backoff
Provides-Extra: test
Requires-Dist: pytest ; extra == 'test'
Requires-Dist: pytest-aiohttp ; extra == 'test'
Requires-Dist: pytest-docker-fixtures ; extra == 'test'
Requires-Dist: async-asgi-testclient ; extra == 'test'
